LLMs/LLMInitialization.py
LLMs/LLMModels.py
LLMs/LLMOutput.py
LLMs/__init__.py
AllLLMs-0.1.1.dist-info/LICENSE
AllLLMs-0.1.1.dist-info/METADATA
AllLLMs-0.1.1.dist-info/WHEEL
AllLLMs-0.1.1.dist-info/top_level.txt
AllLLMs-0.1.1.dist-info/RECORD
