Metadata-Version: 2.1
Name: AllLLMs
Version: 0.1.1
Summary: A wrapper for various large language models including GPT, Claude, and Gemini
Home-page: https://github.com/yourusername/llm-wrapper
Author: Jayam Gupta
Author-email: guptajayam47@gmail.com
Classifier: Programming Language :: Python :: 3
Classifier: License :: OSI Approved :: MIT License
Classifier: Operating System :: OS Independent
Requires-Python: >=3.6
License-File: LICENSE
Requires-Dist: openai
Requires-Dist: anthropic
Requires-Dist: google-generativeai
